pyjokes/__init__.py
pyjokes/cli/__init__.py
pyjokes/exc.py
pyjokes/jokes_cs.py
pyjokes/jokes_de.py
pyjokes/jokes_en.py
pyjokes/jokes_es.py
pyjokes/jokes_eu.py
pyjokes/jokes_fr.py
pyjokes/jokes_gl.py
pyjokes/jokes_hu.py
pyjokes/jokes_it.py
pyjokes/jokes_lt.py
pyjokes/jokes_pl.py
pyjokes/jokes_ru.py
pyjokes/jokes_sv.py
pyjokes/pyjokes.py
pyjokes-0.8.2.dist-info/LICENCE.txt
pyjokes-0.8.2.dist-info/METADATA
pyjokes-0.8.2.dist-info/WHEEL
pyjokes-0.8.2.dist-info/entry_points.txt
pyjokes-0.8.2.dist-info/RECORD
