Metadata-Version: 2.1
Name: pyjokes
Version: 0.8.2
Summary: One line jokes for programmers (jokes as a service)
License: BSD-3-Clause
Author: Ben Nuttall
Author-email: ben@bennuttall.com
Requires-Python: >=3.9,<4.0
Classifier: License :: OSI Approved :: BSD License
Classifier: Programming Language :: Python :: 3
Classifier: Programming Language :: Python :: 3.9
Classifier: Programming Language :: Python :: 3.10
Classifier: Programming Language :: Python :: 3.11
Classifier: Programming Language :: Python :: 3.12
